basescript/__init__.py
basescript/basescript.py
basescript/log.py
basescript-0.3.9.dist-info/LICENSE
basescript-0.3.9.dist-info/METADATA
basescript-0.3.9.dist-info/WHEEL
basescript-0.3.9.dist-info/entry_points.txt
basescript-0.3.9.dist-info/top_level.txt
basescript-0.3.9.dist-info/RECORD
